{
  "generated_at": "2026-03-08T07:55:19.094161",
  "date": "08/03/2026",
  "total": 87,
  "fixtures": [
    {
      "home": "US Lecce",
      "away": "US Cremonese",
      "league": "Serie A",
      "fixture_id": 537094,
      "date": "08/03/2026",
      "time": "12:30",
      "pred": {
        "home": 0.5449,
        "draw": 0.27,
        "away": 0.1851,
        "dc1x": 0.8149,
        "dcx2": 0.4551,
        "dc12": 0.73,
        "over25": 0.349,
        "under25": 0.651,
        "bttsY": 0.4214,
        "bttsN": 0.5786,
        "xg_h": "1.04",
        "xg_a": "1.06",
        "conf": 0.0929,
        "best": "1",
        "bestP": 0.5449
      }
    },
    {
      "home": "Bologna FC 1909",
      "away": "Hellas Verona FC",
      "league": "Serie A",
      "fixture_id": 537090,
      "date": "08/03/2026",
      "time": "15:00",
      "pred": {
        "home": 0.5718,
        "draw": 0.272,
        "away": 0.1562,
        "dc1x": 0.8438,
        "dcx2": 0.4282,
        "dc12": 0.728,
        "over25": 0.4613,
        "under25": 0.5387,
        "bttsY": 0.4883,
        "bttsN": 0.5117,
        "xg_h": "1.56",
        "xg_a": "0.96",
        "conf": 0.1227,
        "best": "1",
        "bestP": 0.5718
      }
    },
    {
      "home": "ACF Fiorentina",
      "away": "Parma Calcio 1913",
      "league": "Serie A",
      "fixture_id": 537085,
      "date": "08/03/2026",
      "time": "15:00",
      "pred": {
        "home": 0.5764,
        "draw": 0.26,
        "away": 0.1636,
        "dc1x": 0.8364,
        "dcx2": 0.4236,
        "dc12": 0.74,
        "over25": 0.404,
        "under25": 0.596,
        "bttsY": 0.467,
        "bttsN": 0.533,
        "xg_h": "1.15",
        "xg_a": "1.15",
        "conf": 0.1225,
        "best": "1",
        "bestP": 0.5764
      }
    },
    {
      "home": "Genoa CFC",
      "away": "AS Roma",
      "league": "Serie A",
      "fixture_id": 537089,
      "date": "08/03/2026",
      "time": "18:00",
      "pred": {
        "home": 0.2511,
        "draw": 0.256,
        "away": 0.4929,
        "dc1x": 0.5071,
        "dcx2": 0.7489,
        "dc12": 0.744,
        "over25": 0.4172,
        "under25": 0.5828,
        "bttsY": 0.4613,
        "bttsN": 0.5387,
        "xg_h": "0.94",
        "xg_a": "1.41",
        "conf": 0.0492,
        "best": "2",
        "bestP": 0.4929
      }
    },
    {
      "home": "AC Milan",
      "away": "FC Internazionale Milano",
      "league": "Serie A",
      "fixture_id": 537086,
      "date": "08/03/2026",
      "time": "20:45",
      "pred": {
        "home": 0.3367,
        "draw": 0.2716,
        "away": 0.3917,
        "dc1x": 0.6083,
        "dcx2": 0.6633,
        "dc12": 0.7284,
        "over25": 0.5161,
        "under25": 0.4839,
        "bttsY": 0.5476,
        "bttsN": 0.4524,
        "xg_h": "1.19",
        "xg_a": "1.56",
        "conf": 0.01,
        "best": "2",
        "bestP": 0.3917
      }
    },
    {
      "home": "SS Lazio",
      "away": "US Sassuolo Calcio",
      "league": "Serie A",
      "fixture_id": 537092,
      "date": "09/03/2026",
      "time": "20:45",
      "pred": {
        "home": 0.5363,
        "draw": 0.26,
        "away": 0.2037,
        "dc1x": 0.7963,
        "dcx2": 0.4637,
        "dc12": 0.74,
        "over25": 0.3973,
        "under25": 0.6027,
        "bttsY": 0.4615,
        "bttsN": 0.5385,
        "xg_h": "1.15",
        "xg_a": "1.13",
        "conf": 0.082,
        "best": "1",
        "bestP": 0.5363
      }
    },
    {
      "home": "Torino FC",
      "away": "Parma Calcio 1913",
      "league": "Serie A",
      "fixture_id": 537096,
      "date": "13/03/2026",
      "time": "20:45",
      "pred": {
        "home": 0.493,
        "draw": 0.269,
        "away": 0.238,
        "dc1x": 0.762,
        "dcx2": 0.507,
        "dc12": 0.731,
        "over25": 0.4145,
        "under25": 0.5855,
        "bttsY": 0.4738,
        "bttsN": 0.5262,
        "xg_h": "1.09",
        "xg_a": "1.25",
        "conf": 0.0501,
        "best": "1",
        "bestP": 0.493
      }
    },
    {
      "home": "FC Internazionale Milano",
      "away": "Atalanta BC",
      "league": "Serie A",
      "fixture_id": 537098,
      "date": "14/03/2026",
      "time": "15:00",
      "pred": {
        "home": 0.6052,
        "draw": 0.266,
        "away": 0.1288,
        "dc1x": 0.8712,
        "dcx2": 0.3948,
        "dc12": 0.734,
        "over25": 0.5149,
        "under25": 0.4851,
        "bttsY": 0.5349,
        "bttsN": 0.4651,
        "xg_h": "1.65",
        "xg_a": "1.08",
        "conf": 0.1625,
        "best": "1",
        "bestP": 0.6052
      }
    },
    {
      "home": "SSC Napoli",
      "away": "US Lecce",
      "league": "Serie A",
      "fixture_id": 537102,
      "date": "14/03/2026",
      "time": "18:00",
      "pred": {
        "home": 0.7159,
        "draw": 0.2356,
        "away": 0.0485,
        "dc1x": 0.9515,
        "dcx2": 0.2841,
        "dc12": 0.7644,
        "over25": 0.4013,
        "under25": 0.5987,
        "bttsY": 0.4379,
        "bttsN": 0.5621,
        "xg_h": "1.44",
        "xg_a": "0.85",
        "conf": 0.3387,
        "best": "1",
        "bestP": 0.7159
      }
    },
    {
      "home": "Udinese Calcio",
      "away": "Juventus FC",
      "league": "Serie A",
      "fixture_id": 537103,
      "date": "14/03/2026",
      "time": "20:45",
      "pred": {
        "home": 0.22,
        "draw": 0.25,
        "away": 0.53,
        "dc1x": 0.47,
        "dcx2": 0.78,
        "dc12": 0.75,
        "over25": 0.51,
        "under25": 0.49,
        "bttsY": 0.5331,
        "bttsN": 0.4669,
        "xg_h": "1.09",
        "xg_a": "1.62",
        "conf": 0.075,
        "best": "2",
        "bestP": 0.53
      }
    },
    {
      "home": "Sunderland AFC",
      "away": "Brighton & Hove Albion FC",
      "league": "Premier League",
      "fixture_id": 538075,
      "date": "14/03/2026",
      "time": "16:00",
      "pred": {
        "home": 0.3476,
        "draw": 0.268,
        "away": 0.3844,
        "dc1x": 0.6156,
        "dcx2": 0.6524,
        "dc12": 0.732,
        "over25": 0.4237,
        "under25": 0.5763,
        "bttsY": 0.4822,
        "bttsN": 0.5178,
        "xg_h": "1.14",
        "xg_a": "1.24",
        "conf": 0.0099,
        "best": "2",
        "bestP": 0.3844
      }
    },
    {
      "home": "Burnley FC",
      "away": "AFC Bournemouth",
      "league": "Premier League",
      "fixture_id": 538079,
      "date": "14/03/2026",
      "time": "16:00",
      "pred": {
        "home": 0.4178,
        "draw": 0.278,
        "away": 0.3042,
        "dc1x": 0.6958,
        "dcx2": 0.5822,
        "dc12": 0.722,
        "over25": 0.5999,
        "under25": 0.4001,
        "bttsY": 0.6122,
        "bttsN": 0.3878,
        "xg_h": "1.35",
        "xg_a": "1.76",
        "conf": 0.0146,
        "best": "1",
        "bestP": 0.4178
      }
    },
    {
      "home": "Arsenal FC",
      "away": "Everton FC",
      "league": "Premier League",
      "fixture_id": 538077,
      "date": "14/03/2026",
      "time": "18:30",
      "pred": {
        "home": 0.7147,
        "draw": 0.2365,
        "away": 0.0489,
        "dc1x": 0.9511,
        "dcx2": 0.2853,
        "dc12": 0.7635,
        "over25": 0.4575,
        "under25": 0.5425,
        "bttsY": 0.4837,
        "bttsN": 0.5163,
        "xg_h": "1.55",
        "xg_a": "0.95",
        "conf": 0.3368,
        "best": "1",
        "bestP": 0.7147
      }
    },
    {
      "home": "Chelsea FC",
      "away": "Newcastle United FC",
      "league": "Premier League",
      "fixture_id": 538080,
      "date": "14/03/2026",
      "time": "18:30",
      "pred": {
        "home": 0.5426,
        "draw": 0.271,
        "away": 0.1864,
        "dc1x": 0.8136,
        "dcx2": 0.4574,
        "dc12": 0.729,
        "over25": 0.5689,
        "under25": 0.4311,
        "bttsY": 0.5906,
        "bttsN": 0.4094,
        "xg_h": "1.66",
        "xg_a": "1.31",
        "conf": 0.0909,
        "best": "1",
        "bestP": 0.5426
      }
    },
    {
      "home": "West Ham United FC",
      "away": "Manchester City FC",
      "league": "Premier League",
      "fixture_id": 538084,
      "date": "14/03/2026",
      "time": "21:00",
      "pred": {
        "home": 0.1573,
        "draw": 0.244,
        "away": 0.5987,
        "dc1x": 0.4013,
        "dcx2": 0.8427,
        "dc12": 0.756,
        "over25": 0.5802,
        "under25": 0.4198,
        "bttsY": 0.5631,
        "bttsN": 0.4369,
        "xg_h": "1.07",
        "xg_a": "1.94",
        "conf": 0.1424,
        "best": "2",
        "bestP": 0.5987
      }
    },
    {
      "home": "Crystal Palace FC",
      "away": "Leeds United FC",
      "league": "Premier League",
      "fixture_id": 538076,
      "date": "15/03/2026",
      "time": "15:00",
      "pred": {
        "home": 0.3219,
        "draw": 0.259,
        "away": 0.4191,
        "dc1x": 0.5809,
        "dcx2": 0.6781,
        "dc12": 0.741,
        "over25": 0.4928,
        "under25": 0.5072,
        "bttsY": 0.5365,
        "bttsN": 0.4635,
        "xg_h": "1.4",
        "xg_a": "1.25",
        "conf": 0.0176,
        "best": "2",
        "bestP": 0.4191
      }
    },
    {
      "home": "Manchester United FC",
      "away": "Aston Villa FC",
      "league": "Premier League",
      "fixture_id": 538082,
      "date": "15/03/2026",
      "time": "15:00",
      "pred": {
        "home": 0.5177,
        "draw": 0.276,
        "away": 0.2063,
        "dc1x": 0.7937,
        "dcx2": 0.4823,
        "dc12": 0.724,
        "over25": 0.5365,
        "under25": 0.4635,
        "bttsY": 0.5716,
        "bttsN": 0.4284,
        "xg_h": "1.46",
        "xg_a": "1.36",
        "conf": 0.07,
        "best": "1",
        "bestP": 0.5177
      }
    },
    {
      "home": "Nottingham Forest FC",
      "away": "Fulham FC",
      "league": "Premier League",
      "fixture_id": 538083,
      "date": "15/03/2026",
      "time": "15:00",
      "pred": {
        "home": 0.387,
        "draw": 0.276,
        "away": 0.337,
        "dc1x": 0.663,
        "dcx2": 0.613,
        "dc12": 0.724,
        "over25": 0.4953,
        "under25": 0.5047,
        "bttsY": 0.5372,
        "bttsN": 0.4628,
        "xg_h": "1.23",
        "xg_a": "1.43",
        "conf": 0.0085,
        "best": "1",
        "bestP": 0.387
      }
    },
    {
      "home": "Liverpool FC",
      "away": "Tottenham Hotspur FC",
      "league": "Premier League",
      "fixture_id": 538081,
      "date": "15/03/2026",
      "time": "17:30",
      "pred": {
        "home": 0.6017,
        "draw": 0.268,
        "away": 0.1303,
        "dc1x": 0.8697,
        "dcx2": 0.3983,
        "dc12": 0.732,
        "over25": 0.5689,
        "under25": 0.4311,
        "bttsY": 0.5928,
        "bttsN": 0.4072,
        "xg_h": "1.62",
        "xg_a": "1.34",
        "conf": 0.1589,
        "best": "1",
        "bestP": 0.6017
      }
    },
    {
      "home": "Villarreal CF",
      "away": "Elche CF",
      "league": "La Liga",
      "fixture_id": 544477,
      "date": "08/03/2026",
      "time": "14:00",
      "pred": {
        "home": 0.602,
        "draw": 0.266,
        "away": 0.132,
        "dc1x": 0.868,
        "dcx2": 0.398,
        "dc12": 0.734,
        "over25": 0.5598,
        "under25": 0.4402,
        "bttsY": 0.5799,
        "bttsN": 0.4201,
        "xg_h": "1.68",
        "xg_a": "1.25",
        "conf": 0.158,
        "best": "1",
        "bestP": 0.602
      }
    },
    {
      "home": "Getafe CF",
      "away": "Real Betis Balompi\u00e9",
      "league": "La Liga",
      "fixture_id": 544476,
      "date": "08/03/2026",
      "time": "16:15",
      "pred": {
        "home": 0.1219,
        "draw": 0.234,
        "away": 0.6441,
        "dc1x": 0.3559,
        "dcx2": 0.8781,
        "dc12": 0.766,
        "over25": 0.4277,
        "under25": 0.5723,
        "bttsY": 0.4769,
        "bttsN": 0.5231,
        "xg_h": "1.02",
        "xg_a": "1.37",
        "conf": 0.1993,
        "best": "2",
        "bestP": 0.6441
      }
    },
    {
      "home": "Sevilla FC",
      "away": "Rayo Vallecano de Madrid",
      "league": "La Liga",
      "fixture_id": 544480,
      "date": "08/03/2026",
      "time": "18:30",
      "pred": {
        "home": 0.2602,
        "draw": 0.252,
        "away": 0.4878,
        "dc1x": 0.5122,
        "dcx2": 0.7398,
        "dc12": 0.748,
        "over25": 0.4715,
        "under25": 0.5285,
        "bttsY": 0.5212,
        "bttsN": 0.4788,
        "xg_h": "1.27",
        "xg_a": "1.29",
        "conf": 0.0463,
        "best": "2",
        "bestP": 0.4878
      }
    },
    {
      "home": "Valencia CF",
      "away": "Deportivo Alav\u00e9s",
      "league": "La Liga",
      "fixture_id": 544475,
      "date": "08/03/2026",
      "time": "21:00",
      "pred": {
        "home": 0.4503,
        "draw": 0.28,
        "away": 0.2697,
        "dc1x": 0.7303,
        "dcx2": 0.5497,
        "dc12": 0.72,
        "over25": 0.4211,
        "under25": 0.5789,
        "bttsY": 0.4809,
        "bttsN": 0.5191,
        "xg_h": "1.18",
        "xg_a": "1.19",
        "conf": 0.0268,
        "best": "1",
        "bestP": 0.4503
      }
    },
    {
      "home": "RCD Espanyol de Barcelona",
      "away": "Real Oviedo",
      "league": "La Liga",
      "fixture_id": 544474,
      "date": "09/03/2026",
      "time": "21:00",
      "pred": {
        "home": 0.4222,
        "draw": 0.275,
        "away": 0.3028,
        "dc1x": 0.6972,
        "dcx2": 0.5778,
        "dc12": 0.725,
        "over25": 0.4613,
        "under25": 0.5387,
        "bttsY": 0.5018,
        "bttsN": 0.4982,
        "xg_h": "1.46",
        "xg_a": "1.06",
        "conf": 0.0162,
        "best": "1",
        "bestP": 0.4222
      }
    },
    {
      "home": "Deportivo Alav\u00e9s",
      "away": "Villarreal CF",
      "league": "La Liga",
      "fixture_id": 544481,
      "date": "13/03/2026",
      "time": "21:00",
      "pred": {
        "home": 0.3035,
        "draw": 0.266,
        "away": 0.4305,
        "dc1x": 0.5695,
        "dcx2": 0.6965,
        "dc12": 0.734,
        "over25": 0.4853,
        "under25": 0.5147,
        "bttsY": 0.512,
        "bttsN": 0.488,
        "xg_h": "1.03",
        "xg_a": "1.58",
        "conf": 0.0197,
        "best": "2",
        "bestP": 0.4305
      }
    },
    {
      "home": "Girona FC",
      "away": "Athletic Club",
      "league": "La Liga",
      "fixture_id": 544486,
      "date": "14/03/2026",
      "time": "14:00",
      "pred": {
        "home": 0.3439,
        "draw": 0.268,
        "away": 0.3881,
        "dc1x": 0.6119,
        "dcx2": 0.6561,
        "dc12": 0.732,
        "over25": 0.4702,
        "under25": 0.5298,
        "bttsY": 0.5188,
        "bttsN": 0.4812,
        "xg_h": "1.21",
        "xg_a": "1.35",
        "conf": 0.0103,
        "best": "2",
        "bestP": 0.3881
      }
    },
    {
      "home": "Club Atl\u00e9tico de Madrid",
      "away": "Getafe CF",
      "league": "La Liga",
      "fixture_id": 544482,
      "date": "14/03/2026",
      "time": "16:15",
      "pred": {
        "home": 0.723,
        "draw": 0.2282,
        "away": 0.0488,
        "dc1x": 0.9512,
        "dcx2": 0.277,
        "dc12": 0.7718,
        "over25": 0.3987,
        "under25": 0.6013,
        "bttsY": 0.4392,
        "bttsN": 0.5608,
        "xg_h": "1.41",
        "xg_a": "0.87",
        "conf": 0.3455,
        "best": "1",
        "bestP": 0.723
      }
    },
    {
      "home": "Real Oviedo",
      "away": "Valencia CF",
      "league": "La Liga",
      "fixture_id": 544485,
      "date": "14/03/2026",
      "time": "18:30",
      "pred": {
        "home": 0.7019,
        "draw": 0.234,
        "away": 0.0641,
        "dc1x": 0.9359,
        "dcx2": 0.2981,
        "dc12": 0.766,
        "over25": 0.4316,
        "under25": 0.5684,
        "bttsY": 0.4833,
        "bttsN": 0.5167,
        "xg_h": "1.06",
        "xg_a": "1.34",
        "conf": 0.3042,
        "best": "1",
        "bestP": 0.7019
      }
    },
    {
      "home": "Real Madrid CF",
      "away": "Elche CF",
      "league": "La Liga",
      "fixture_id": 544487,
      "date": "14/03/2026",
      "time": "21:00",
      "pred": {
        "home": 0.7349,
        "draw": 0.2184,
        "away": 0.0467,
        "dc1x": 0.9533,
        "dcx2": 0.2651,
        "dc12": 0.7816,
        "over25": 0.5459,
        "under25": 0.4541,
        "bttsY": 0.5496,
        "bttsN": 0.4504,
        "xg_h": "1.78",
        "xg_a": "1.08",
        "conf": 0.3613,
        "best": "1",
        "bestP": 0.7349
      }
    },
    {
      "home": "FC St. Pauli 1910",
      "away": "Eintracht Frankfurt",
      "league": "Bundesliga",
      "fixture_id": 540623,
      "date": "08/03/2026",
      "time": "15:30",
      "pred": {
        "home": 0.318,
        "draw": 0.264,
        "away": 0.418,
        "dc1x": 0.582,
        "dcx2": 0.682,
        "dc12": 0.736,
        "over25": 0.6476,
        "under25": 0.3524,
        "bttsY": 0.6529,
        "bttsN": 0.3471,
        "xg_h": "1.5",
        "xg_a": "1.83",
        "conf": 0.0164,
        "best": "2",
        "bestP": 0.418
      }
    },
    {
      "home": "1. FC Union Berlin",
      "away": "SV Werder Bremen",
      "league": "Bundesliga",
      "fixture_id": 540625,
      "date": "08/03/2026",
      "time": "17:30",
      "pred": {
        "home": 0.4506,
        "draw": 0.28,
        "away": 0.2694,
        "dc1x": 0.7306,
        "dcx2": 0.5494,
        "dc12": 0.72,
        "over25": 0.5377,
        "under25": 0.4623,
        "bttsY": 0.5705,
        "bttsN": 0.4295,
        "xg_h": "1.52",
        "xg_a": "1.31",
        "conf": 0.027,
        "best": "1",
        "bestP": 0.4506
      }
    },
    {
      "home": "Borussia M\u00f6nchengladbach",
      "away": "FC St. Pauli 1910",
      "league": "Bundesliga",
      "fixture_id": 540637,
      "date": "13/03/2026",
      "time": "20:30",
      "pred": {
        "home": 0.6199,
        "draw": 0.25,
        "away": 0.1301,
        "dc1x": 0.8699,
        "dcx2": 0.3801,
        "dc12": 0.75,
        "over25": 0.5149,
        "under25": 0.4851,
        "bttsY": 0.5552,
        "bttsN": 0.4448,
        "xg_h": "1.4",
        "xg_a": "1.34",
        "conf": 0.1732,
        "best": "1",
        "bestP": 0.6199
      }
    },
    {
      "home": "Bayer 04 Leverkusen",
      "away": "FC Bayern M\u00fcnchen",
      "league": "Bundesliga",
      "fixture_id": 540631,
      "date": "14/03/2026",
      "time": "15:30",
      "pred": {
        "home": 0.3133,
        "draw": 0.274,
        "away": 0.4127,
        "dc1x": 0.5873,
        "dcx2": 0.6867,
        "dc12": 0.726,
        "over25": 0.7499,
        "under25": 0.2501,
        "bttsY": 0.6992,
        "bttsN": 0.3008,
        "xg_h": "1.44",
        "xg_a": "2.48",
        "conf": 0.0137,
        "best": "2",
        "bestP": 0.4127
      }
    },
    {
      "home": "TSG 1899 Hoffenheim",
      "away": "VfL Wolfsburg",
      "league": "Bundesliga",
      "fixture_id": 540634,
      "date": "14/03/2026",
      "time": "15:30",
      "pred": {
        "home": 0.5083,
        "draw": 0.28,
        "away": 0.2117,
        "dc1x": 0.7883,
        "dcx2": 0.4917,
        "dc12": 0.72,
        "over25": 0.6792,
        "under25": 0.3208,
        "bttsY": 0.653,
        "bttsN": 0.347,
        "xg_h": "2.16",
        "xg_a": "1.34",
        "conf": 0.0633,
        "best": "1",
        "bestP": 0.5083
      }
    },
    {
      "home": "Borussia Dortmund",
      "away": "FC Augsburg",
      "league": "Bundesliga",
      "fixture_id": 540635,
      "date": "14/03/2026",
      "time": "15:30",
      "pred": {
        "home": 0.6815,
        "draw": 0.25,
        "away": 0.0685,
        "dc1x": 0.9315,
        "dcx2": 0.3185,
        "dc12": 0.75,
        "over25": 0.5901,
        "under25": 0.4099,
        "bttsY": 0.5805,
        "bttsN": 0.4195,
        "xg_h": "1.92",
        "xg_a": "1.14",
        "conf": 0.2795,
        "best": "1",
        "bestP": 0.6815
      }
    },
    {
      "home": "Eintracht Frankfurt",
      "away": "1. FC Heidenheim 1846",
      "league": "Bundesliga",
      "fixture_id": 540638,
      "date": "14/03/2026",
      "time": "15:30",
      "pred": {
        "home": 0.6304,
        "draw": 0.264,
        "away": 0.1056,
        "dc1x": 0.8944,
        "dcx2": 0.3696,
        "dc12": 0.736,
        "over25": 0.7043,
        "under25": 0.2957,
        "bttsY": 0.6855,
        "bttsN": 0.3145,
        "xg_h": "2.14",
        "xg_a": "1.5",
        "conf": 0.1992,
        "best": "1",
        "bestP": 0.6304
      }
    },
    {
      "home": "Hamburger SV",
      "away": "1. FC K\u00f6ln",
      "league": "Bundesliga",
      "fixture_id": 540639,
      "date": "14/03/2026",
      "time": "18:30",
      "pred": {
        "home": 0.4783,
        "draw": 0.28,
        "away": 0.2417,
        "dc1x": 0.7583,
        "dcx2": 0.5217,
        "dc12": 0.72,
        "over25": 0.5353,
        "under25": 0.4647,
        "bttsY": 0.5713,
        "bttsN": 0.4287,
        "xg_h": "1.42",
        "xg_a": "1.4",
        "conf": 0.0421,
        "best": "1",
        "bestP": 0.4783
      }
    },
    {
      "home": "SV Werder Bremen",
      "away": "1. FSV Mainz 05",
      "league": "Bundesliga",
      "fixture_id": 540632,
      "date": "15/03/2026",
      "time": "15:30",
      "pred": {
        "home": 0.4219,
        "draw": 0.28,
        "away": 0.2981,
        "dc1x": 0.7019,
        "dcx2": 0.5781,
        "dc12": 0.72,
        "over25": 0.5388,
        "under25": 0.4612,
        "bttsY": 0.5726,
        "bttsN": 0.4274,
        "xg_h": "1.34",
        "xg_a": "1.5",
        "conf": 0.0157,
        "best": "1",
        "bestP": 0.4219
      }
    },
    {
      "home": "SC Freiburg",
      "away": "1. FC Union Berlin",
      "league": "Bundesliga",
      "fixture_id": 540636,
      "date": "15/03/2026",
      "time": "17:30",
      "pred": {
        "home": 0.4736,
        "draw": 0.28,
        "away": 0.2464,
        "dc1x": 0.7536,
        "dcx2": 0.5264,
        "dc12": 0.72,
        "over25": 0.5712,
        "under25": 0.4288,
        "bttsY": 0.5988,
        "bttsN": 0.4012,
        "xg_h": "1.53",
        "xg_a": "1.44",
        "conf": 0.0392,
        "best": "1",
        "bestP": 0.4736
      }
    },
    {
      "home": "Racing Club de Lens",
      "away": "FC Metz",
      "league": "Ligue 1",
      "fixture_id": 542629,
      "date": "08/03/2026",
      "time": "15:00",
      "pred": {
        "home": 0.7185,
        "draw": 0.2339,
        "away": 0.0475,
        "dc1x": 0.9525,
        "dcx2": 0.2815,
        "dc12": 0.7661,
        "over25": 0.5644,
        "under25": 0.4356,
        "bttsY": 0.5167,
        "bttsN": 0.4833,
        "xg_h": "2.04",
        "xg_a": "0.9",
        "conf": 0.3427,
        "best": "1",
        "bestP": 0.7185
      }
    },
    {
      "home": "OGC Nice",
      "away": "Stade Rennais FC 1901",
      "league": "Ligue 1",
      "fixture_id": 542625,
      "date": "08/03/2026",
      "time": "17:15",
      "pred": {
        "home": 0.4056,
        "draw": 0.28,
        "away": 0.3144,
        "dc1x": 0.6856,
        "dcx2": 0.5944,
        "dc12": 0.72,
        "over25": 0.5901,
        "under25": 0.4099,
        "bttsY": 0.6072,
        "bttsN": 0.3928,
        "xg_h": "1.35",
        "xg_a": "1.71",
        "conf": 0.0113,
        "best": "1",
        "bestP": 0.4056
      }
    },
    {
      "home": "Lille OSC",
      "away": "FC Lorient",
      "league": "Ligue 1",
      "fixture_id": 542627,
      "date": "08/03/2026",
      "time": "17:15",
      "pred": {
        "home": 0.5494,
        "draw": 0.266,
        "away": 0.1846,
        "dc1x": 0.8154,
        "dcx2": 0.4506,
        "dc12": 0.734,
        "over25": 0.5575,
        "under25": 0.4425,
        "bttsY": 0.5861,
        "bttsN": 0.4139,
        "xg_h": "1.56",
        "xg_a": "1.35",
        "conf": 0.096,
        "best": "1",
        "bestP": 0.5494
      }
    },
    {
      "home": "Stade Brestois 29",
      "away": "Le Havre AC",
      "league": "Ligue 1",
      "fixture_id": 542630,
      "date": "08/03/2026",
      "time": "17:15",
      "pred": {
        "home": 0.5005,
        "draw": 0.28,
        "away": 0.2195,
        "dc1x": 0.7805,
        "dcx2": 0.4995,
        "dc12": 0.72,
        "over25": 0.4342,
        "under25": 0.5658,
        "bttsY": 0.4894,
        "bttsN": 0.5106,
        "xg_h": "1.29",
        "xg_a": "1.12",
        "conf": 0.0573,
        "best": "1",
        "bestP": 0.5005
      }
    },
    {
      "home": "Olympique Lyonnais",
      "away": "Paris FC",
      "league": "Ligue 1",
      "fixture_id": 542626,
      "date": "08/03/2026",
      "time": "20:45",
      "pred": {
        "home": 0.2907,
        "draw": 0.253,
        "away": 0.4563,
        "dc1x": 0.5437,
        "dcx2": 0.7093,
        "dc12": 0.747,
        "over25": 0.5234,
        "under25": 0.4766,
        "bttsY": 0.545,
        "bttsN": 0.455,
        "xg_h": "1.65",
        "xg_a": "1.12",
        "conf": 0.0307,
        "best": "2",
        "bestP": 0.4563
      }
    },
    {
      "home": "Olympique de Marseille",
      "away": "AJ Auxerre",
      "league": "Ligue 1",
      "fixture_id": 542635,
      "date": "13/03/2026",
      "time": "20:45",
      "pred": {
        "home": 0.612,
        "draw": 0.262,
        "away": 0.126,
        "dc1x": 0.874,
        "dcx2": 0.388,
        "dc12": 0.738,
        "over25": 0.5258,
        "under25": 0.4742,
        "bttsY": 0.5331,
        "bttsN": 0.4669,
        "xg_h": "1.74",
        "xg_a": "1.04",
        "conf": 0.1694,
        "best": "1",
        "bestP": 0.612
      }
    },
    {
      "home": "FC Lorient",
      "away": "Racing Club de Lens",
      "league": "Ligue 1",
      "fixture_id": 542633,
      "date": "14/03/2026",
      "time": "17:00",
      "pred": {
        "home": 0.2,
        "draw": 0.246,
        "away": 0.554,
        "dc1x": 0.446,
        "dcx2": 0.8,
        "dc12": 0.754,
        "over25": 0.5494,
        "under25": 0.4506,
        "bttsY": 0.5622,
        "bttsN": 0.4378,
        "xg_h": "1.15",
        "xg_a": "1.73",
        "conf": 0.0952,
        "best": "2",
        "bestP": 0.554
      }
    },
    {
      "home": "Angers SCO",
      "away": "OGC Nice",
      "league": "Ligue 1",
      "fixture_id": 542638,
      "date": "14/03/2026",
      "time": "19:00",
      "pred": {
        "home": 0.4456,
        "draw": 0.28,
        "away": 0.2744,
        "dc1x": 0.7256,
        "dcx2": 0.5544,
        "dc12": 0.72,
        "over25": 0.4816,
        "under25": 0.5184,
        "bttsY": 0.5277,
        "bttsN": 0.4723,
        "xg_h": "1.38",
        "xg_a": "1.23",
        "conf": 0.0247,
        "best": "1",
        "bestP": 0.4456
      }
    },
    {
      "home": "AS Monaco FC",
      "away": "Stade Brestois 29",
      "league": "Ligue 1",
      "fixture_id": 542632,
      "date": "14/03/2026",
      "time": "21:05",
      "pred": {
        "home": 0.6195,
        "draw": 0.258,
        "away": 0.1225,
        "dc1x": 0.8775,
        "dcx2": 0.3805,
        "dc12": 0.742,
        "over25": 0.5712,
        "under25": 0.4288,
        "bttsY": 0.5976,
        "bttsN": 0.4024,
        "xg_h": "1.57",
        "xg_a": "1.41",
        "conf": 0.1777,
        "best": "1",
        "bestP": 0.6195
      }
    },
    {
      "home": "RC Strasbourg Alsace",
      "away": "Paris FC",
      "league": "Ligue 1",
      "fixture_id": 542637,
      "date": "15/03/2026",
      "time": "15:00",
      "pred": {
        "home": 0.1743,
        "draw": 0.235,
        "away": 0.5907,
        "dc1x": 0.4093,
        "dcx2": 0.8257,
        "dc12": 0.765,
        "over25": 0.54,
        "under25": 0.46,
        "bttsY": 0.5638,
        "bttsN": 0.4362,
        "xg_h": "1.64",
        "xg_a": "1.21",
        "conf": 0.13,
        "best": "2",
        "bestP": 0.5907
      }
    },
    {
      "home": "Galatasaray SK",
      "away": "Liverpool FC",
      "league": "Champions League",
      "fixture_id": 552069,
      "date": "10/03/2026",
      "time": "18:45",
      "pred": {
        "home": 0.129,
        "draw": 0.243,
        "away": 0.628,
        "dc1x": 0.372,
        "dcx2": 0.871,
        "dc12": 0.757,
        "over25": 0.6505,
        "under25": 0.3495,
        "bttsY": 0.6338,
        "bttsN": 0.3662,
        "xg_h": "1.3",
        "xg_a": "2.05",
        "conf": 0.1807,
        "best": "2",
        "bestP": 0.628
      }
    },
    {
      "home": "Atalanta BC",
      "away": "FC Bayern M\u00fcnchen",
      "league": "Champions League",
      "fixture_id": 552071,
      "date": "10/03/2026",
      "time": "21:00",
      "pred": {
        "home": 0.219,
        "draw": 0.258,
        "away": 0.523,
        "dc1x": 0.477,
        "dcx2": 0.781,
        "dc12": 0.742,
        "over25": 0.6253,
        "under25": 0.3747,
        "bttsY": 0.6066,
        "bttsN": 0.3934,
        "xg_h": "1.2",
        "xg_a": "2.02",
        "conf": 0.0705,
        "best": "2",
        "bestP": 0.523
      }
    },
    {
      "home": "Newcastle United FC",
      "away": "FC Barcelona",
      "league": "Champions League",
      "fixture_id": 552072,
      "date": "10/03/2026",
      "time": "21:00",
      "pred": {
        "home": 0.305,
        "draw": 0.258,
        "away": 0.437,
        "dc1x": 0.563,
        "dcx2": 0.695,
        "dc12": 0.742,
        "over25": 0.7691,
        "under25": 0.2309,
        "bttsY": 0.7505,
        "bttsN": 0.2495,
        "xg_h": "2.17",
        "xg_a": "1.88",
        "conf": 0.0229,
        "best": "2",
        "bestP": 0.437
      }
    },
    {
      "home": "Club Atl\u00e9tico de Madrid",
      "away": "Tottenham Hotspur FC",
      "league": "Champions League",
      "fixture_id": 552073,
      "date": "10/03/2026",
      "time": "21:00",
      "pred": {
        "home": 0.58,
        "draw": 0.259,
        "away": 0.161,
        "dc1x": 0.839,
        "dcx2": 0.42,
        "dc12": 0.741,
        "over25": 0.706,
        "under25": 0.294,
        "bttsY": 0.698,
        "bttsN": 0.302,
        "xg_h": "1.64",
        "xg_a": "2.01",
        "conf": 0.1263,
        "best": "1",
        "bestP": 0.58
      }
    },
    {
      "home": "Bayer 04 Leverkusen",
      "away": "Arsenal FC",
      "league": "Champions League",
      "fixture_id": 552075,
      "date": "11/03/2026",
      "time": "18:45",
      "pred": {
        "home": 0.3511,
        "draw": 0.278,
        "away": 0.3709,
        "dc1x": 0.6291,
        "dcx2": 0.6489,
        "dc12": 0.722,
        "over25": 0.6074,
        "under25": 0.3926,
        "bttsY": 0.5577,
        "bttsN": 0.4423,
        "xg_h": "1.0",
        "xg_a": "2.14",
        "conf": 0.0067,
        "best": "2",
        "bestP": 0.3709
      }
    },
    {
      "home": "Paris Saint-Germain FC",
      "away": "Chelsea FC",
      "league": "Champions League",
      "fixture_id": 552068,
      "date": "11/03/2026",
      "time": "21:00",
      "pred": {
        "home": 0.5602,
        "draw": 0.263,
        "away": 0.1768,
        "dc1x": 0.8232,
        "dcx2": 0.4398,
        "dc12": 0.737,
        "over25": 0.7204,
        "under25": 0.2796,
        "bttsY": 0.7143,
        "bttsN": 0.2857,
        "xg_h": "1.93",
        "xg_a": "1.81",
        "conf": 0.106,
        "best": "1",
        "bestP": 0.5602
      }
    },
    {
      "home": "Real Madrid CF",
      "away": "Manchester City FC",
      "league": "Champions League",
      "fixture_id": 552070,
      "date": "11/03/2026",
      "time": "21:00",
      "pred": {
        "home": 0.476,
        "draw": 0.278,
        "away": 0.246,
        "dc1x": 0.754,
        "dcx2": 0.524,
        "dc12": 0.722,
        "over25": 0.6505,
        "under25": 0.3495,
        "bttsY": 0.6591,
        "bttsN": 0.3409,
        "xg_h": "1.76",
        "xg_a": "1.59",
        "conf": 0.0404,
        "best": "1",
        "bestP": 0.476
      }
    },
    {
      "home": "FK Bod\u00f8/Glimt",
      "away": "Sporting Clube de Portugal",
      "league": "Champions League",
      "fixture_id": 552074,
      "date": "11/03/2026",
      "time": "21:00",
      "pred": {
        "home": 0.2372,
        "draw": 0.246,
        "away": 0.5168,
        "dc1x": 0.4832,
        "dcx2": 0.7628,
        "dc12": 0.754,
        "over25": 0.6883,
        "under25": 0.3117,
        "bttsY": 0.6867,
        "bttsN": 0.3133,
        "xg_h": "1.64",
        "xg_a": "1.91",
        "conf": 0.0648,
        "best": "2",
        "bestP": 0.5168
      }
    },
    {
      "home": "Sparta Rotterdam",
      "away": "PEC Zwolle",
      "league": "Eredivisie",
      "fixture_id": 537674,
      "date": "08/03/2026",
      "time": "12:15",
      "pred": {
        "home": 0.4431,
        "draw": 0.28,
        "away": 0.2769,
        "dc1x": 0.7231,
        "dcx2": 0.5569,
        "dc12": 0.72,
        "over25": 0.6117,
        "under25": 0.3883,
        "bttsY": 0.6297,
        "bttsN": 0.3703,
        "xg_h": "1.64",
        "xg_a": "1.52",
        "conf": 0.0236,
        "best": "1",
        "bestP": 0.4431
      }
    },
    {
      "home": "Fortuna Sittard",
      "away": "Telstar 1963",
      "league": "Eredivisie",
      "fixture_id": 537668,
      "date": "08/03/2026",
      "time": "14:30",
      "pred": {
        "home": 0.4651,
        "draw": 0.28,
        "away": 0.2549,
        "dc1x": 0.7451,
        "dcx2": 0.5349,
        "dc12": 0.72,
        "over25": 0.6032,
        "under25": 0.3968,
        "bttsY": 0.6235,
        "bttsN": 0.3765,
        "xg_h": "1.6",
        "xg_a": "1.52",
        "conf": 0.0343,
        "best": "1",
        "bestP": 0.4651
      }
    },
    {
      "home": "Go Ahead Eagles",
      "away": "FC Twente '65",
      "league": "Eredivisie",
      "fixture_id": 537669,
      "date": "08/03/2026",
      "time": "14:30",
      "pred": {
        "home": 0.4119,
        "draw": 0.28,
        "away": 0.3081,
        "dc1x": 0.6919,
        "dcx2": 0.5881,
        "dc12": 0.72,
        "over25": 0.5494,
        "under25": 0.4506,
        "bttsY": 0.5762,
        "bttsN": 0.4238,
        "xg_h": "1.28",
        "xg_a": "1.6",
        "conf": 0.0128,
        "best": "1",
        "bestP": 0.4119
      }
    },
    {
      "home": "NAC Breda",
      "away": "Feyenoord Rotterdam",
      "league": "Eredivisie",
      "fixture_id": 537671,
      "date": "08/03/2026",
      "time": "16:45",
      "pred": {
        "home": 0.2149,
        "draw": 0.252,
        "away": 0.5331,
        "dc1x": 0.4669,
        "dcx2": 0.7851,
        "dc12": 0.748,
        "over25": 0.5945,
        "under25": 0.4055,
        "bttsY": 0.5922,
        "bttsN": 0.4078,
        "xg_h": "1.2",
        "xg_a": "1.88",
        "conf": 0.0779,
        "best": "2",
        "bestP": 0.5331
      }
    },
    {
      "home": "NEC",
      "away": "FC Volendam",
      "league": "Eredivisie",
      "fixture_id": 537672,
      "date": "08/03/2026",
      "time": "20:00",
      "pred": {
        "home": 0.4539,
        "draw": 0.28,
        "away": 0.2661,
        "dc1x": 0.7339,
        "dcx2": 0.5461,
        "dc12": 0.72,
        "over25": 0.6754,
        "under25": 0.3246,
        "bttsY": 0.6639,
        "bttsN": 0.3361,
        "xg_h": "2.04",
        "xg_a": "1.44",
        "conf": 0.0286,
        "best": "1",
        "bestP": 0.4539
      }
    },
    {
      "home": "PEC Zwolle",
      "away": "FC Groningen",
      "league": "Eredivisie",
      "fixture_id": 537680,
      "date": "13/03/2026",
      "time": "20:00",
      "pred": {
        "home": 0.4649,
        "draw": 0.28,
        "away": 0.2551,
        "dc1x": 0.7449,
        "dcx2": 0.5351,
        "dc12": 0.72,
        "over25": 0.5901,
        "under25": 0.4099,
        "bttsY": 0.6083,
        "bttsN": 0.3917,
        "xg_h": "1.37",
        "xg_a": "1.69",
        "conf": 0.0342,
        "best": "1",
        "bestP": 0.4649
      }
    },
    {
      "home": "FC Volendam",
      "away": "Fortuna Sittard",
      "league": "Eredivisie",
      "fixture_id": 537677,
      "date": "14/03/2026",
      "time": "16:30",
      "pred": {
        "home": 0.4535,
        "draw": 0.28,
        "away": 0.2665,
        "dc1x": 0.7335,
        "dcx2": 0.5465,
        "dc12": 0.72,
        "over25": 0.5945,
        "under25": 0.4055,
        "bttsY": 0.6164,
        "bttsN": 0.3836,
        "xg_h": "1.48",
        "xg_a": "1.6",
        "conf": 0.0284,
        "best": "1",
        "bestP": 0.4535
      }
    },
    {
      "home": "PSV",
      "away": "NEC",
      "league": "Eredivisie",
      "fixture_id": 537681,
      "date": "14/03/2026",
      "time": "18:45",
      "pred": {
        "home": 0.4987,
        "draw": 0.28,
        "away": 0.2213,
        "dc1x": 0.7787,
        "dcx2": 0.5013,
        "dc12": 0.72,
        "over25": 0.7783,
        "under25": 0.2217,
        "bttsY": 0.7532,
        "bttsN": 0.2468,
        "xg_h": "2.3",
        "xg_a": "1.81",
        "conf": 0.0559,
        "best": "1",
        "bestP": 0.4987
      }
    },
    {
      "home": "SC Heerenveen",
      "away": "Telstar 1963",
      "league": "Eredivisie",
      "fixture_id": 537682,
      "date": "14/03/2026",
      "time": "20:00",
      "pred": {
        "home": 0.499,
        "draw": 0.28,
        "away": 0.221,
        "dc1x": 0.779,
        "dcx2": 0.501,
        "dc12": 0.72,
        "over25": 0.6053,
        "under25": 0.3947,
        "bttsY": 0.6234,
        "bttsN": 0.3766,
        "xg_h": "1.67",
        "xg_a": "1.46",
        "conf": 0.0561,
        "best": "1",
        "bestP": 0.499
      }
    },
    {
      "home": "AFC Ajax",
      "away": "Sparta Rotterdam",
      "league": "Eredivisie",
      "fixture_id": 537675,
      "date": "14/03/2026",
      "time": "21:00",
      "pred": {
        "home": 0.6492,
        "draw": 0.254,
        "away": 0.0968,
        "dc1x": 0.9032,
        "dcx2": 0.3508,
        "dc12": 0.746,
        "over25": 0.5901,
        "under25": 0.4099,
        "bttsY": 0.6018,
        "bttsN": 0.3982,
        "xg_h": "1.77",
        "xg_a": "1.29",
        "conf": 0.2221,
        "best": "1",
        "bestP": 0.6492
      }
    },
    {
      "home": "CF Estrela da Amadora",
      "away": "Gil Vicente FC",
      "league": "Primeira Liga",
      "fixture_id": 545920,
      "date": "08/03/2026",
      "time": "16:30",
      "pred": {
        "home": 0.4141,
        "draw": 0.28,
        "away": 0.3059,
        "dc1x": 0.6941,
        "dcx2": 0.5859,
        "dc12": 0.72,
        "over25": 0.4828,
        "under25": 0.5172,
        "bttsY": 0.5084,
        "bttsN": 0.4916,
        "xg_h": "1.02",
        "xg_a": "1.58",
        "conf": 0.0134,
        "best": "1",
        "bestP": 0.4141
      }
    },
    {
      "home": "Sport Lisboa e Benfica",
      "away": "FC Porto",
      "league": "Primeira Liga",
      "fixture_id": 545924,
      "date": "08/03/2026",
      "time": "19:00",
      "pred": {
        "home": 0.4778,
        "draw": 0.279,
        "away": 0.2432,
        "dc1x": 0.7568,
        "dcx2": 0.5222,
        "dc12": 0.721,
        "over25": 0.4549,
        "under25": 0.5451,
        "bttsY": 0.5079,
        "bttsN": 0.4921,
        "xg_h": "1.23",
        "xg_a": "1.27",
        "conf": 0.0416,
        "best": "1",
        "bestP": 0.4778
      }
    },
    {
      "home": "CD Santa Clara",
      "away": "Vit\u00f3ria SC",
      "league": "Primeira Liga",
      "fixture_id": 545922,
      "date": "08/03/2026",
      "time": "21:30",
      "pred": {
        "home": 0.4053,
        "draw": 0.28,
        "away": 0.3147,
        "dc1x": 0.6853,
        "dcx2": 0.5947,
        "dc12": 0.72,
        "over25": 0.4237,
        "under25": 0.5763,
        "bttsY": 0.4825,
        "bttsN": 0.5175,
        "xg_h": "1.15",
        "xg_a": "1.23",
        "conf": 0.0112,
        "best": "1",
        "bestP": 0.4053
      }
    },
    {
      "home": "CD Tondela",
      "away": "Rio Ave FC",
      "league": "Primeira Liga",
      "fixture_id": 545919,
      "date": "09/03/2026",
      "time": "21:15",
      "pred": {
        "home": 0.4904,
        "draw": 0.28,
        "away": 0.2296,
        "dc1x": 0.7704,
        "dcx2": 0.5096,
        "dc12": 0.72,
        "over25": 0.4765,
        "under25": 0.5235,
        "bttsY": 0.5251,
        "bttsN": 0.4749,
        "xg_h": "1.31",
        "xg_a": "1.27",
        "conf": 0.05,
        "best": "1",
        "bestP": 0.4904
      }
    },
    {
      "home": "Vit\u00f3ria SC",
      "away": "FC Famalic\u00e3o",
      "league": "Primeira Liga",
      "fixture_id": 545928,
      "date": "14/03/2026",
      "time": "16:30",
      "pred": {
        "home": 0.4246,
        "draw": 0.28,
        "away": 0.2954,
        "dc1x": 0.7046,
        "dcx2": 0.5754,
        "dc12": 0.72,
        "over25": 0.4132,
        "under25": 0.5868,
        "bttsY": 0.4663,
        "bttsN": 0.5337,
        "xg_h": "1.0",
        "xg_a": "1.33",
        "conf": 0.0166,
        "best": "1",
        "bestP": 0.4246
      }
    },
    {
      "home": "Gil Vicente FC",
      "away": "FC Alverca",
      "league": "Primeira Liga",
      "fixture_id": 545927,
      "date": "14/03/2026",
      "time": "19:00",
      "pred": {
        "home": 0.4805,
        "draw": 0.28,
        "away": 0.2395,
        "dc1x": 0.7605,
        "dcx2": 0.5195,
        "dc12": 0.72,
        "over25": 0.4485,
        "under25": 0.5515,
        "bttsY": 0.4808,
        "bttsN": 0.5192,
        "xg_h": "1.51",
        "xg_a": "0.96",
        "conf": 0.0434,
        "best": "1",
        "bestP": 0.4805
      }
    },
    {
      "home": "FC Arouca",
      "away": "Sport Lisboa e Benfica",
      "league": "Primeira Liga",
      "fixture_id": 545932,
      "date": "14/03/2026",
      "time": "21:30",
      "pred": {
        "home": 0.1731,
        "draw": 0.25,
        "away": 0.5769,
        "dc1x": 0.4231,
        "dcx2": 0.8269,
        "dc12": 0.75,
        "over25": 0.5879,
        "under25": 0.4121,
        "bttsY": 0.5328,
        "bttsN": 0.4672,
        "xg_h": "0.93",
        "xg_a": "2.12",
        "conf": 0.1193,
        "best": "2",
        "bestP": 0.5769
      }
    },
    {
      "home": "CD Nacional",
      "away": "GD Estoril Praia",
      "league": "Primeira Liga",
      "fixture_id": 545925,
      "date": "15/03/2026",
      "time": "16:30",
      "pred": {
        "home": 0.4051,
        "draw": 0.28,
        "away": 0.3149,
        "dc1x": 0.6851,
        "dcx2": 0.5949,
        "dc12": 0.72,
        "over25": 0.5945,
        "under25": 0.4055,
        "bttsY": 0.6141,
        "bttsN": 0.3859,
        "xg_h": "1.42",
        "xg_a": "1.66",
        "conf": 0.0112,
        "best": "1",
        "bestP": 0.4051
      }
    },
    {
      "home": "AVS",
      "away": "CD Santa Clara",
      "league": "Primeira Liga",
      "fixture_id": 545931,
      "date": "15/03/2026",
      "time": "16:30",
      "pred": {
        "home": 0.4622,
        "draw": 0.28,
        "away": 0.2578,
        "dc1x": 0.7422,
        "dcx2": 0.5378,
        "dc12": 0.72,
        "over25": 0.4715,
        "under25": 0.5285,
        "bttsY": 0.5001,
        "bttsN": 0.4999,
        "xg_h": "1.0",
        "xg_a": "1.55",
        "conf": 0.0328,
        "best": "1",
        "bestP": 0.4622
      }
    },
    {
      "home": "Rio Ave FC",
      "away": "CF Estrela da Amadora",
      "league": "Primeira Liga",
      "fixture_id": 545926,
      "date": "15/03/2026",
      "time": "19:00",
      "pred": {
        "home": 0.4119,
        "draw": 0.28,
        "away": 0.3081,
        "dc1x": 0.6919,
        "dcx2": 0.5881,
        "dc12": 0.72,
        "over25": 0.5282,
        "under25": 0.4718,
        "bttsY": 0.5649,
        "bttsN": 0.4351,
        "xg_h": "1.33",
        "xg_a": "1.46",
        "conf": 0.0128,
        "best": "1",
        "bestP": 0.4119
      }
    },
    {
      "home": "Queens Park Rangers FC",
      "away": "Middlesbrough FC",
      "league": "Championship",
      "fixture_id": 541139,
      "date": "08/03/2026",
      "time": "17:30",
      "pred": {
        "home": 0.4086,
        "draw": 0.28,
        "away": 0.3114,
        "dc1x": 0.6886,
        "dcx2": 0.5914,
        "dc12": 0.72,
        "over25": 0.5051,
        "under25": 0.4949,
        "bttsY": 0.5381,
        "bttsN": 0.4619,
        "xg_h": "1.16",
        "xg_a": "1.54",
        "conf": 0.012,
        "best": "1",
        "bestP": 0.4086
      }
    },
    {
      "home": "Leicester City FC",
      "away": "Bristol City FC",
      "league": "Championship",
      "fixture_id": 541145,
      "date": "10/03/2026",
      "time": "20:45",
      "pred": {
        "home": 0.1614,
        "draw": 0.235,
        "away": 0.6036,
        "dc1x": 0.3964,
        "dcx2": 0.8386,
        "dc12": 0.765,
        "over25": 0.521,
        "under25": 0.479,
        "bttsY": 0.5587,
        "bttsN": 0.4413,
        "xg_h": "1.31",
        "xg_a": "1.46",
        "conf": 0.1449,
        "best": "2",
        "bestP": 0.6036
      }
    },
    {
      "home": "Millwall FC",
      "away": "Derby County FC",
      "league": "Championship",
      "fixture_id": 541146,
      "date": "10/03/2026",
      "time": "20:45",
      "pred": {
        "home": 0.4622,
        "draw": 0.28,
        "away": 0.2578,
        "dc1x": 0.7422,
        "dcx2": 0.5378,
        "dc12": 0.72,
        "over25": 0.499,
        "under25": 0.501,
        "bttsY": 0.5429,
        "bttsN": 0.4571,
        "xg_h": "1.35",
        "xg_a": "1.32",
        "conf": 0.0328,
        "best": "1",
        "bestP": 0.4622
      }
    },
    {
      "home": "Portsmouth FC",
      "away": "Swansea City AFC",
      "league": "Championship",
      "fixture_id": 541148,
      "date": "10/03/2026",
      "time": "20:45",
      "pred": {
        "home": 0.1398,
        "draw": 0.236,
        "away": 0.6242,
        "dc1x": 0.3758,
        "dcx2": 0.8602,
        "dc12": 0.764,
        "over25": 0.4026,
        "under25": 0.5974,
        "bttsY": 0.4637,
        "bttsN": 0.5363,
        "xg_h": "1.06",
        "xg_a": "1.23",
        "conf": 0.1716,
        "best": "2",
        "bestP": 0.6242
      }
    },
    {
      "home": "Sheffield Wednesday FC",
      "away": "Watford FC",
      "league": "Championship",
      "fixture_id": 541149,
      "date": "10/03/2026",
      "time": "20:45",
      "pred": {
        "home": 0.3751,
        "draw": 0.28,
        "away": 0.3449,
        "dc1x": 0.6551,
        "dcx2": 0.6249,
        "dc12": 0.72,
        "over25": 0.4689,
        "under25": 0.5311,
        "bttsY": 0.4773,
        "bttsN": 0.5227,
        "xg_h": "0.89",
        "xg_a": "1.66",
        "conf": 0.0066,
        "best": "1",
        "bestP": 0.3751
      }
    },
    {
      "home": "Wrexham AFC",
      "away": "Hull City AFC",
      "league": "Championship",
      "fixture_id": 541151,
      "date": "10/03/2026",
      "time": "20:45",
      "pred": {
        "home": 0.1955,
        "draw": 0.236,
        "away": 0.5685,
        "dc1x": 0.4315,
        "dcx2": 0.8045,
        "dc12": 0.764,
        "over25": 0.5598,
        "under25": 0.4402,
        "bttsY": 0.5902,
        "bttsN": 0.4098,
        "xg_h": "1.49",
        "xg_a": "1.44",
        "conf": 0.1071,
        "best": "2",
        "bestP": 0.5685
      }
    },
    {
      "home": "Stoke City FC",
      "away": "Ipswich Town FC",
      "league": "Championship",
      "fixture_id": 541150,
      "date": "10/03/2026",
      "time": "21:00",
      "pred": {
        "home": 0.6894,
        "draw": 0.228,
        "away": 0.0826,
        "dc1x": 0.9174,
        "dcx2": 0.3106,
        "dc12": 0.772,
        "over25": 0.4329,
        "under25": 0.5671,
        "bttsY": 0.4823,
        "bttsN": 0.5177,
        "xg_h": "1.04",
        "xg_a": "1.37",
        "conf": 0.2723,
        "best": "1",
        "bestP": 0.6894
      }
    },
    {
      "home": "Birmingham City FC",
      "away": "Queens Park Rangers FC",
      "league": "Championship",
      "fixture_id": 541144,
      "date": "11/03/2026",
      "time": "20:45",
      "pred": {
        "home": 0.7142,
        "draw": 0.2358,
        "away": 0.05,
        "dc1x": 0.95,
        "dcx2": 0.2858,
        "dc12": 0.7642,
        "over25": 0.5113,
        "under25": 0.4887,
        "bttsY": 0.5519,
        "bttsN": 0.4481,
        "xg_h": "1.41",
        "xg_a": "1.31",
        "conf": 0.3348,
        "best": "1",
        "bestP": 0.7142
      }
    },
    {
      "home": "Norwich City FC",
      "away": "Sheffield United FC",
      "league": "Championship",
      "fixture_id": 541147,
      "date": "11/03/2026",
      "time": "20:45",
      "pred": {
        "home": 0.6054,
        "draw": 0.258,
        "away": 0.1366,
        "dc1x": 0.8634,
        "dcx2": 0.3946,
        "dc12": 0.742,
        "over25": 0.5039,
        "under25": 0.4961,
        "bttsY": 0.5468,
        "bttsN": 0.4532,
        "xg_h": "1.35",
        "xg_a": "1.34",
        "conf": 0.1578,
        "best": "1",
        "bestP": 0.6054
      }
    },
    {
      "home": "Middlesbrough FC",
      "away": "Charlton Athletic FC",
      "league": "Championship",
      "fixture_id": 541153,
      "date": "11/03/2026",
      "time": "20:45",
      "pred": {
        "home": 0.384,
        "draw": 0.268,
        "away": 0.348,
        "dc1x": 0.652,
        "dcx2": 0.616,
        "dc12": 0.732,
        "over25": 0.4106,
        "under25": 0.5894,
        "bttsY": 0.4608,
        "bttsN": 0.5392,
        "xg_h": "1.35",
        "xg_a": "0.97",
        "conf": 0.0099,
        "best": "1",
        "bestP": 0.384
      }
    }
  ]
}