[
  {
    "league": "Serie A",
    "fixture_id": 537093,
    "home": "SSC Napoli",
    "away": "Torino FC",
    "date": "06/03/2026",
    "time": "20:45",
    "prediction": {
      "home": 0.6514612635526893,
      "draw": 0.251,
      "away": 0.0975387364473107,
      "quantum_used": false,
      "dc_1x": 0.9024612635526893,
      "dc_x2": 0.3485387364473107,
      "dc_12": 0.749,
      "over_25": 0.48157042406394956,
      "under_25": 0.5184295759360504,
      "btts_y": 0.523066520741483,
      "btts_n": 0.47693347925851703,
      "xg_home": 1.45,
      "xg_away": 1.15,
      "confidence": 0.22342455343495204,
      "best_out": "1",
      "best_val": 0.6514612635526893
    },
    "generated_at": "2026-03-03T23:59:15.331398"
  },
  {
    "league": "Premier League",
    "fixture_id": 538066,
    "home": "Aston Villa FC",
    "away": "Chelsea FC",
    "date": "04/03/2026",
    "time": "20:30",
    "prediction": {
      "home": 0.3793871841659987,
      "draw": 0.27,
      "away": 0.3506128158340013,
      "quantum_used": false,
      "dc_1x": 0.6493871841659987,
      "dc_x2": 0.6206128158340013,
      "dc_12": 0.73,
      "over_25": 0.506375508926538,
      "under_25": 0.49362449107346196,
      "btts_y": 0.5487249914479668,
      "btts_n": 0.4512750085520332,
      "xg_home": 1.35,
      "xg_away": 1.35,
      "confidence": 0.009032533671168408,
      "best_out": "1",
      "best_val": 0.3793871841659987
    },
    "generated_at": "2026-03-03T23:59:22.948981"
  },
  {
    "league": "Premier League",
    "fixture_id": 538067,
    "home": "Brighton & Hove Albion FC",
    "away": "Arsenal FC",
    "date": "04/03/2026",
    "time": "20:30",
    "prediction": {
      "home": 0.25860320329074316,
      "draw": 0.254,
      "away": 0.48739679670925684,
      "quantum_used": false,
      "dc_1x": 0.5126032032907432,
      "dc_x2": 0.7413967967092568,
      "dc_12": 0.746,
      "over_25": 0.5423791164789342,
      "under_25": 0.4576208835210658,
      "btts_y": 0.569443006019993,
      "btts_n": 0.430556993980007,
      "xg_home": 1.25,
      "xg_away": 1.6,
      "confidence": 0.04596164399135794,
      "best_out": "2",
      "best_val": 0.48739679670925684
    },
    "generated_at": "2026-03-03T23:59:23.412355"
  },
  {
    "league": "Premier League",
    "fixture_id": 538069,
    "home": "Fulham FC",
    "away": "West Ham United FC",
    "date": "04/03/2026",
    "time": "20:30",
    "prediction": {
      "home": 0.4324631174083814,
      "draw": 0.278,
      "away": 0.2895368825916186,
      "quantum_used": false,
      "dc_1x": 0.7104631174083814,
      "dc_x2": 0.5675368825916186,
      "dc_12": 0.722,
      "over_25": 0.4561868841166705,
      "under_25": 0.5438131158833295,
      "btts_y": 0.5090754049035185,
      "btts_n": 0.49092459509648145,
      "xg_home": 1.25,
      "xg_away": 1.25,
      "confidence": 0.01943014146675437,
      "best_out": "1",
      "best_val": 0.4324631174083814
    },
    "generated_at": "2026-03-03T23:59:23.871633"
  },
  {
    "league": "La Liga",
    "fixture_id": 544440,
    "home": "Rayo Vallecano de Madrid",
    "away": "Real Oviedo",
    "date": "04/03/2026",
    "time": "19:00",
    "prediction": {
      "home": 0.4454986786718095,
      "draw": 0.28,
      "away": 0.2745013213281905,
      "quantum_used": false,
      "dc_1x": 0.7254986786718095,
      "dc_x2": 0.5545013213281905,
      "dc_12": 0.72,
      "over_25": 0.5768099188731565,
      "under_25": 0.42319008112684353,
      "btts_y": 0.6035267480710044,
      "btts_n": 0.39647325192899563,
      "xg_home": 1.5,
      "xg_away": 1.5,
      "confidence": 0.024661979152743596,
      "best_out": "1",
      "best_val": 0.4454986786718095
    },
    "generated_at": "2026-03-03T23:59:31.360585"
  },
  {
    "league": "La Liga",
    "fixture_id": 544473,
    "home": "RC Celta de Vigo",
    "away": "Real Madrid CF",
    "date": "06/03/2026",
    "time": "21:00",
    "prediction": {
      "home": 0.12916992772326885,
      "draw": 0.23400000000000004,
      "away": 0.636830072276731,
      "quantum_used": false,
      "dc_1x": 0.3631699277232689,
      "dc_x2": 0.870830072276731,
      "dc_12": 0.7659999999999999,
      "over_25": 0.5185432952869836,
      "under_25": 0.4814567047130164,
      "btts_y": 0.5313065880428177,
      "btts_n": 0.4686934119571823,
      "xg_home": 1.05,
      "xg_away": 1.7,
      "confidence": 0.18842770175205492,
      "best_out": "2",
      "best_val": 0.636830072276731
    },
    "generated_at": "2026-03-03T23:59:31.822341"
  },
  {
    "league": "Bundesliga",
    "fixture_id": 540558,
    "home": "Hamburger SV",
    "away": "Bayer 04 Leverkusen",
    "date": "04/03/2026",
    "time": "20:30",
    "prediction": {
      "home": 0.1848605754168779,
      "draw": 0.24400000000000002,
      "away": 0.5711394245831221,
      "quantum_used": false,
      "dc_1x": 0.42886057541687794,
      "dc_x2": 0.815139424583122,
      "dc_12": 0.756,
      "over_25": 0.5185432952869836,
      "under_25": 0.4814567047130164,
      "btts_y": 0.5313065880428177,
      "btts_n": 0.4686934119571823,
      "xg_home": 1.05,
      "xg_away": 1.7,
      "confidence": 0.1114572720565129,
      "best_out": "2",
      "best_val": 0.5711394245831221
    },
    "generated_at": "2026-03-03T23:59:38.947203"
  },
  {
    "league": "Bundesliga",
    "fixture_id": 540627,
    "home": "FC Bayern M\u00fcnchen",
    "away": "Borussia M\u00f6nchengladbach",
    "date": "06/03/2026",
    "time": "20:30",
    "prediction": {
      "home": 0.5471394245831221,
      "draw": 0.268,
      "away": 0.18486057541687784,
      "quantum_used": false,
      "dc_1x": 0.8151394245831222,
      "dc_x2": 0.45286057541687785,
      "dc_12": 0.732,
      "over_25": 0.5423791164789342,
      "under_25": 0.4576208835210658,
      "btts_y": 0.569443006019993,
      "btts_n": 0.430556993980007,
      "xg_home": 1.6,
      "xg_away": 1.25,
      "confidence": 0.09438458282983841,
      "best_out": "1",
      "best_val": 0.5471394245831221
    },
    "generated_at": "2026-03-03T23:59:39.407975"
  },
  {
    "league": "Ligue 1",
    "fixture_id": 542628,
    "home": "Paris Saint-Germain FC",
    "away": "AS Monaco FC",
    "date": "06/03/2026",
    "time": "20:45",
    "prediction": {
      "home": 0.6190072897556675,
      "draw": 0.257,
      "away": 0.12399271024433245,
      "quantum_used": false,
      "dc_1x": 0.8760072897556676,
      "dc_x2": 0.38099271024433246,
      "dc_12": 0.743,
      "over_25": 0.5423791164789342,
      "under_25": 0.4576208835210658,
      "btts_y": 0.569443006019993,
      "btts_n": 0.430556993980007,
      "xg_home": 1.6,
      "xg_away": 1.25,
      "confidence": 0.17630729633002906,
      "best_out": "1",
      "best_val": 0.6190072897556675
    },
    "generated_at": "2026-03-03T23:59:46.937699"
  },
  {
    "league": "Eredivisie",
    "fixture_id": 537670,
    "home": "Heracles Almelo",
    "away": "FC Utrecht",
    "date": "06/03/2026",
    "time": "20:00",
    "prediction": {
      "home": 0.4454986786718095,
      "draw": 0.28,
      "away": 0.2745013213281905,
      "quantum_used": false,
      "dc_1x": 0.7254986786718095,
      "dc_x2": 0.5545013213281905,
      "dc_12": 0.72,
      "over_25": 0.4561868841166705,
      "under_25": 0.5438131158833295,
      "btts_y": 0.5090754049035185,
      "btts_n": 0.49092459509648145,
      "xg_home": 1.25,
      "xg_away": 1.25,
      "confidence": 0.024661979152743596,
      "best_out": "1",
      "best_val": 0.4454986786718095
    },
    "generated_at": "2026-03-04T00:00:08.018531"
  },
  {
    "league": "Eredivisie",
    "fixture_id": 537667,
    "home": "FC Groningen",
    "away": "AFC Ajax",
    "date": "07/03/2026",
    "time": "16:30",
    "prediction": {
      "home": 0.26160320329074316,
      "draw": 0.254,
      "away": 0.48439679670925684,
      "quantum_used": false,
      "dc_1x": 0.5156032032907432,
      "dc_x2": 0.7383967967092568,
      "dc_12": 0.746,
      "over_25": 0.48157042406394956,
      "under_25": 0.5184295759360504,
      "btts_y": 0.523066520741483,
      "btts_n": 0.47693347925851703,
      "xg_home": 1.15,
      "xg_away": 1.45,
      "confidence": 0.04425515921414447,
      "best_out": "2",
      "best_val": 0.48439679670925684
    },
    "generated_at": "2026-03-04T00:00:08.501787"
  },
  {
    "league": "Eredivisie",
    "fixture_id": 537673,
    "home": "PSV",
    "away": "AZ",
    "date": "07/03/2026",
    "time": "20:00",
    "prediction": {
      "home": 0.4454986786718095,
      "draw": 0.28,
      "away": 0.2745013213281905,
      "quantum_used": false,
      "dc_1x": 0.7254986786718095,
      "dc_x2": 0.5545013213281905,
      "dc_12": 0.72,
      "over_25": 0.4561868841166705,
      "under_25": 0.5438131158833295,
      "btts_y": 0.5090754049035185,
      "btts_n": 0.49092459509648145,
      "xg_home": 1.25,
      "xg_away": 1.25,
      "confidence": 0.024661979152743596,
      "best_out": "1",
      "best_val": 0.4454986786718095
    },
    "generated_at": "2026-03-04T00:00:08.966642"
  },
  {
    "league": "Primeira Liga",
    "fixture_id": 545918,
    "home": "FC Famalic\u00e3o",
    "away": "FC Arouca",
    "date": "06/03/2026",
    "time": "21:15",
    "prediction": {
      "home": 0.4454986786718095,
      "draw": 0.28,
      "away": 0.2745013213281905,
      "quantum_used": false,
      "dc_1x": 0.7254986786718095,
      "dc_x2": 0.5545013213281905,
      "dc_12": 0.72,
      "over_25": 0.4561868841166705,
      "under_25": 0.5438131158833295,
      "btts_y": 0.5090754049035185,
      "btts_n": 0.49092459509648145,
      "xg_home": 1.25,
      "xg_away": 1.25,
      "confidence": 0.024661979152743596,
      "best_out": "1",
      "best_val": 0.4454986786718095
    },
    "generated_at": "2026-03-04T00:00:16.986530"
  },
  {
    "league": "Primeira Liga",
    "fixture_id": 545916,
    "home": "FC Alverca",
    "away": "AVS",
    "date": "07/03/2026",
    "time": "16:30",
    "prediction": {
      "home": 0.4454986786718095,
      "draw": 0.28,
      "away": 0.2745013213281905,
      "quantum_used": false,
      "dc_1x": 0.7254986786718095,
      "dc_x2": 0.5545013213281905,
      "dc_12": 0.72,
      "over_25": 0.4561868841166705,
      "under_25": 0.5438131158833295,
      "btts_y": 0.5090754049035185,
      "btts_n": 0.49092459509648145,
      "xg_home": 1.25,
      "xg_away": 1.25,
      "confidence": 0.024661979152743596,
      "best_out": "1",
      "best_val": 0.4454986786718095
    },
    "generated_at": "2026-03-04T00:00:17.473282"
  },
  {
    "league": "Primeira Liga",
    "fixture_id": 545921,
    "home": "Moreirense FC",
    "away": "CD Nacional",
    "date": "07/03/2026",
    "time": "16:30",
    "prediction": {
      "home": 0.4454986786718095,
      "draw": 0.28,
      "away": 0.2745013213281905,
      "quantum_used": false,
      "dc_1x": 0.7254986786718095,
      "dc_x2": 0.5545013213281905,
      "dc_12": 0.72,
      "over_25": 0.4561868841166705,
      "under_25": 0.5438131158833295,
      "btts_y": 0.5090754049035185,
      "btts_n": 0.49092459509648145,
      "xg_home": 1.25,
      "xg_away": 1.25,
      "confidence": 0.024661979152743596,
      "best_out": "1",
      "best_val": 0.4454986786718095
    },
    "generated_at": "2026-03-04T00:00:17.935231"
  },
  {
    "league": "Championship",
    "fixture_id": 541138,
    "home": "Preston North End FC",
    "away": "Oxford United FC",
    "date": "06/03/2026",
    "time": "21:00",
    "prediction": {
      "home": 0.2875368825916186,
      "draw": 0.258,
      "away": 0.4544631174083814,
      "quantum_used": false,
      "dc_1x": 0.5455368825916186,
      "dc_x2": 0.7124631174083814,
      "dc_12": 0.742,
      "over_25": 0.48157042406394956,
      "under_25": 0.5184295759360504,
      "btts_y": 0.523066520741483,
      "btts_n": 0.47693347925851703,
      "xg_home": 1.15,
      "xg_away": 1.45,
      "confidence": 0.029383176887338047,
      "best_out": "2",
      "best_val": 0.4544631174083814
    },
    "generated_at": "2026-03-04T00:00:25.021640"
  },
  {
    "league": "Championship",
    "fixture_id": 541132,
    "home": "Blackburn Rovers FC",
    "away": "Portsmouth FC",
    "date": "07/03/2026",
    "time": "13:30",
    "prediction": {
      "home": 0.4454986786718095,
      "draw": 0.28,
      "away": 0.2745013213281905,
      "quantum_used": false,
      "dc_1x": 0.7254986786718095,
      "dc_x2": 0.5545013213281905,
      "dc_12": 0.72,
      "over_25": 0.4561868841166705,
      "under_25": 0.5438131158833295,
      "btts_y": 0.5090754049035185,
      "btts_n": 0.49092459509648145,
      "xg_home": 1.25,
      "xg_away": 1.25,
      "confidence": 0.024661979152743596,
      "best_out": "1",
      "best_val": 0.4454986786718095
    },
    "generated_at": "2026-03-04T00:00:25.484289"
  },
  {
    "league": "Championship",
    "fixture_id": 541136,
    "home": "Hull City AFC",
    "away": "Millwall FC",
    "date": "07/03/2026",
    "time": "13:30",
    "prediction": {
      "home": 0.721969053437879,
      "draw": 0.22942413772258943,
      "away": 0.04860680883953166,
      "quantum_used": false,
      "dc_1x": 0.9513931911604684,
      "dc_x2": 0.2780309465621211,
      "dc_12": 0.7705758622774106,
      "over_25": 0.5185432952869836,
      "under_25": 0.4814567047130164,
      "btts_y": 0.5313065880428177,
      "btts_n": 0.4686934119571823,
      "xg_home": 1.7,
      "xg_away": 1.05,
      "confidence": 0.34468337771276203,
      "best_out": "1",
      "best_val": 0.721969053437879
    },
    "generated_at": "2026-03-04T00:00:25.935668"
  }
]